pyhearthis/__init__.py
pyhearthis/hearthis.py
pyhearthis/hearthis_requests.py
pyhearthis/models.py
pyhearthis-0.0.5.dist-info/LICENSE
pyhearthis-0.0.5.dist-info/METADATA
pyhearthis-0.0.5.dist-info/WHEEL
pyhearthis-0.0.5.dist-info/top_level.txt
pyhearthis-0.0.5.dist-info/RECORD
